{
  "generated_at_utc": "2026-03-06T12:53:45Z",
  "source": "yfinance",
  "interval": "1d",
  "lookback": "400d",
  "trading_days": 252,
  "count": 11,
  "data": [
    {
      "symbol": "CL=F",
      "name": "Crude Oil WTI",
      "price": 86.389999,
      "close_d1": 81.010002,
      "change_pts": 5.379997,
      "change_pct": 0.06641152,
      "daily_7d": [
        {
          "date": "2026-02-26",
          "close": 65.209999
        },
        {
          "date": "2026-02-27",
          "close": 67.019997
        },
        {
          "date": "2026-03-02",
          "close": 71.230003
        },
        {
          "date": "2026-03-03",
          "close": 74.559998
        },
        {
          "date": "2026-03-04",
          "close": 74.660004
        },
        {
          "date": "2026-03-05",
          "close": 81.010002
        },
        {
          "date": "2026-03-06",
          "close": 86.389999
        }
      ],
      "vol_annual": 0.32903327,
      "vol_semiannual": 0.33334922,
      "vol_quarterly": 0.38635316,
      "vol_monthly": 0.47720015,
      "vol_weekly": 0.48328966
    },
    {
      "symbol": "BZ=F",
      "name": "Crude Oil Brent",
      "price": 89.360001,
      "close_d1": 85.410004,
      "change_pts": 3.949997,
      "change_pct": 0.04624747,
      "daily_7d": [
        {
          "date": "2026-02-26",
          "close": 70.75
        },
        {
          "date": "2026-02-27",
          "close": 72.480003
        },
        {
          "date": "2026-03-02",
          "close": 77.739998
        },
        {
          "date": "2026-03-03",
          "close": 81.400002
        },
        {
          "date": "2026-03-04",
          "close": 81.400002
        },
        {
          "date": "2026-03-05",
          "close": 85.410004
        },
        {
          "date": "2026-03-06",
          "close": 89.360001
        }
      ],
      "vol_annual": 0.30158477,
      "vol_semiannual": 0.31353248,
      "vol_quarterly": 0.36137747,
      "vol_monthly": 0.40677628,
      "vol_weekly": 0.4058605
    },
    {
      "symbol": "NG=F",
      "name": "Natural Gas",
      "price": 3.08,
      "close_d1": 3.003,
      "change_pts": 0.077,
      "change_pct": 0.02564099,
      "daily_7d": [
        {
          "date": "2026-02-26",
          "close": 2.827
        },
        {
          "date": "2026-02-27",
          "close": 2.859
        },
        {
          "date": "2026-03-02",
          "close": 2.96
        },
        {
          "date": "2026-03-03",
          "close": 3.054
        },
        {
          "date": "2026-03-04",
          "close": 2.917
        },
        {
          "date": "2026-03-05",
          "close": 3.003
        },
        {
          "date": "2026-03-06",
          "close": 3.08
        }
      ],
      "vol_annual": 1.00895916,
      "vol_semiannual": 1.36456262,
      "vol_quarterly": 1.81840308,
      "vol_monthly": 0.53636021,
      "vol_weekly": 0.54215612
    },
    {
      "symbol": "GC=F",
      "name": "Gold",
      "price": 5101.799805,
      "close_d1": 5065.299805,
      "change_pts": 36.5,
      "change_pct": 0.00720589,
      "daily_7d": [
        {
          "date": "2026-02-26",
          "close": 5176.5
        },
        {
          "date": "2026-02-27",
          "close": 5230.5
        },
        {
          "date": "2026-03-02",
          "close": 5294.399902
        },
        {
          "date": "2026-03-03",
          "close": 5107.399902
        },
        {
          "date": "2026-03-04",
          "close": 5120.200195
        },
        {
          "date": "2026-03-05",
          "close": 5065.299805
        },
        {
          "date": "2026-03-06",
          "close": 5101.799805
        }
      ],
      "vol_annual": 0.24260246,
      "vol_semiannual": 0.31040718,
      "vol_quarterly": 0.37220617,
      "vol_monthly": 0.2884734,
      "vol_weekly": 0.30642377
    },
    {
      "symbol": "SI=F",
      "name": "Silver",
      "price": 82.885002,
      "close_d1": 81.686996,
      "change_pts": 1.198006,
      "change_pct": 0.01466581,
      "daily_7d": [
        {
          "date": "2026-02-26",
          "close": 86.998001
        },
        {
          "date": "2026-02-27",
          "close": 92.681999
        },
        {
          "date": "2026-03-02",
          "close": 88.283997
        },
        {
          "date": "2026-03-03",
          "close": 82.922997
        },
        {
          "date": "2026-03-04",
          "close": 82.633003
        },
        {
          "date": "2026-03-05",
          "close": 81.686996
        },
        {
          "date": "2026-03-06",
          "close": 82.800003
        }
      ],
      "vol_annual": 0.56550318,
      "vol_semiannual": 0.84425726,
      "vol_quarterly": 1.12734896,
      "vol_monthly": 0.8248248,
      "vol_weekly": 0.5065993
    },
    {
      "symbol": "HG=F",
      "name": "Copper",
      "price": 5.8095,
      "close_d1": 5.753,
      "change_pts": 0.0565,
      "change_pct": 0.00982104,
      "daily_7d": [
        {
          "date": "2026-02-26",
          "close": 5.947
        },
        {
          "date": "2026-02-27",
          "close": 6.0045
        },
        {
          "date": "2026-03-02",
          "close": 5.8945
        },
        {
          "date": "2026-03-03",
          "close": 5.7735
        },
        {
          "date": "2026-03-04",
          "close": 5.855
        },
        {
          "date": "2026-03-05",
          "close": 5.753
        },
        {
          "date": "2026-03-06",
          "close": 5.8095
        }
      ],
      "vol_annual": 0.37059671,
      "vol_semiannual": 0.30691011,
      "vol_quarterly": 0.35540869,
      "vol_monthly": 0.2693591,
      "vol_weekly": 0.26974248
    },
    {
      "symbol": "ZS=F",
      "name": "Soybeans",
      "price": 1190.5,
      "close_d1": 1163.75,
      "change_pts": 26.75,
      "change_pct": 0.02298604,
      "daily_7d": [
        {
          "date": "2026-02-26",
          "close": 1147.75
        },
        {
          "date": "2026-02-27",
          "close": 1157.25
        },
        {
          "date": "2026-03-02",
          "close": 1150.0
        },
        {
          "date": "2026-03-03",
          "close": 1155.75
        },
        {
          "date": "2026-03-04",
          "close": 1154.5
        },
        {
          "date": "2026-03-05",
          "close": 1163.75
        },
        {
          "date": "2026-03-06",
          "close": 1190.5
        }
      ],
      "vol_annual": 0.16180785,
      "vol_semiannual": 0.15382497,
      "vol_quarterly": 0.14085619,
      "vol_monthly": 0.11875131,
      "vol_weekly": 0.17483719
    },
    {
      "symbol": "ZC=F",
      "name": "Corn",
      "price": 458.25,
      "close_d1": 441.5,
      "change_pts": 16.75,
      "change_pct": 0.03793884,
      "daily_7d": [
        {
          "date": "2026-02-26",
          "close": 433.25
        },
        {
          "date": "2026-02-27",
          "close": 438.75
        },
        {
          "date": "2026-03-02",
          "close": 433.25
        },
        {
          "date": "2026-03-03",
          "close": 434.25
        },
        {
          "date": "2026-03-04",
          "close": 431.75
        },
        {
          "date": "2026-03-05",
          "close": 441.5
        },
        {
          "date": "2026-03-06",
          "close": 458.25
        }
      ],
      "vol_annual": 0.19793426,
      "vol_semiannual": 0.18650925,
      "vol_quarterly": 0.18694979,
      "vol_monthly": 0.18437395,
      "vol_weekly": 0.32772934
    },
    {
      "symbol": "ZW=F",
      "name": "Wheat",
      "price": 601.25,
      "close_d1": 582.75,
      "change_pts": 18.5,
      "change_pct": 0.03174603,
      "daily_7d": [
        {
          "date": "2026-02-26",
          "close": 571.75
        },
        {
          "date": "2026-02-27",
          "close": 591.25
        },
        {
          "date": "2026-03-02",
          "close": 574.5
        },
        {
          "date": "2026-03-03",
          "close": 572.25
        },
        {
          "date": "2026-03-04",
          "close": 566.75
        },
        {
          "date": "2026-03-05",
          "close": 582.75
        },
        {
          "date": "2026-03-06",
          "close": 601.25
        }
      ],
      "vol_annual": 0.23525603,
      "vol_semiannual": 0.2191818,
      "vol_quarterly": 0.22296458,
      "vol_monthly": 0.28540715,
      "vol_weekly": 0.40705948
    },
    {
      "symbol": "KC=F",
      "name": "Coffee",
      "price": 295.75,
      "close_d1": 293.0,
      "change_pts": 2.75,
      "change_pct": 0.00938567,
      "daily_7d": [
        {
          "date": "2026-02-26",
          "close": 286.0
        },
        {
          "date": "2026-02-27",
          "close": 284.600006
        },
        {
          "date": "2026-03-02",
          "close": 288.350006
        },
        {
          "date": "2026-03-03",
          "close": 286.950012
        },
        {
          "date": "2026-03-04",
          "close": 290.700012
        },
        {
          "date": "2026-03-05",
          "close": 293.0
        },
        {
          "date": "2026-03-06",
          "close": 295.75
        }
      ],
      "vol_annual": 0.37756203,
      "vol_semiannual": 0.37548265,
      "vol_quarterly": 0.34178274,
      "vol_monthly": 0.29635998,
      "vol_weekly": 0.11709315
    },
    {
      "symbol": "SB=F",
      "name": "Sugar",
      "price": 13.85,
      "close_d1": 13.72,
      "change_pts": 0.13,
      "change_pct": 0.00947523,
      "daily_7d": [
        {
          "date": "2026-02-26",
          "close": 14.41
        },
        {
          "date": "2026-02-27",
          "close": 14.3
        },
        {
          "date": "2026-03-02",
          "close": 13.91
        },
        {
          "date": "2026-03-03",
          "close": 13.93
        },
        {
          "date": "2026-03-04",
          "close": 13.73
        },
        {
          "date": "2026-03-05",
          "close": 13.72
        },
        {
          "date": "2026-03-06",
          "close": 13.85
        }
      ],
      "vol_annual": 0.2419849,
      "vol_semiannual": 0.22279663,
      "vol_quarterly": 0.21349927,
      "vol_monthly": 0.20869152,
      "vol_weekly": 0.23287527
    }
  ]
}