{
  "generated_at_utc": "2026-03-25T12:04:22Z",
  "source": "yfinance",
  "interval": "1d",
  "lookback": "400d",
  "trading_days": 252,
  "count": 11,
  "data": [
    {
      "symbol": "CL=F",
      "name": "Crude Oil WTI",
      "price": 87.459999,
      "close_d1": 92.349998,
      "change_pts": -4.889999,
      "change_pct": -0.05295073,
      "daily_7d": [
        {
          "date": "2026-03-17",
          "close": 96.209999
        },
        {
          "date": "2026-03-18",
          "close": 96.32
        },
        {
          "date": "2026-03-19",
          "close": 96.139999
        },
        {
          "date": "2026-03-20",
          "close": 98.32
        },
        {
          "date": "2026-03-23",
          "close": 88.129997
        },
        {
          "date": "2026-03-24",
          "close": 92.349998
        },
        {
          "date": "2026-03-25",
          "close": 87.459999
        }
      ],
      "vol_annual": 0.38941936,
      "vol_semiannual": 0.47653373,
      "vol_quarterly": 0.61710865,
      "vol_monthly": 0.96171712,
      "vol_weekly": 0.99652978
    },
    {
      "symbol": "BZ=F",
      "name": "Crude Oil Brent",
      "price": 94.610001,
      "close_d1": 104.489998,
      "change_pts": -9.879997,
      "change_pct": -0.09455448,
      "daily_7d": [
        {
          "date": "2026-03-17",
          "close": 103.419998
        },
        {
          "date": "2026-03-18",
          "close": 107.379997
        },
        {
          "date": "2026-03-19",
          "close": 108.650002
        },
        {
          "date": "2026-03-20",
          "close": 112.190002
        },
        {
          "date": "2026-03-23",
          "close": 99.940002
        },
        {
          "date": "2026-03-24",
          "close": 104.489998
        },
        {
          "date": "2026-03-25",
          "close": 94.610001
        }
      ],
      "vol_annual": 0.37048237,
      "vol_semiannual": 0.47095908,
      "vol_quarterly": 0.61192253,
      "vol_monthly": 0.94886592,
      "vol_weekly": 1.20837441
    },
    {
      "symbol": "NG=F",
      "name": "Natural Gas",
      "price": 2.854,
      "close_d1": 2.943,
      "change_pts": -0.089,
      "change_pct": -0.03024125,
      "daily_7d": [
        {
          "date": "2026-03-17",
          "close": 3.033
        },
        {
          "date": "2026-03-18",
          "close": 3.065
        },
        {
          "date": "2026-03-19",
          "close": 3.166
        },
        {
          "date": "2026-03-20",
          "close": 3.095
        },
        {
          "date": "2026-03-23",
          "close": 2.891
        },
        {
          "date": "2026-03-24",
          "close": 2.943
        },
        {
          "date": "2026-03-25",
          "close": 2.854
        }
      ],
      "vol_annual": 1.00304338,
      "vol_semiannual": 1.37191296,
      "vol_quarterly": 1.81344837,
      "vol_monthly": 0.57863822,
      "vol_weekly": 0.63785729
    },
    {
      "symbol": "GC=F",
      "name": "Gold",
      "price": 4575.0,
      "close_d1": 4399.299805,
      "change_pts": 175.700195,
      "change_pct": 0.03993822,
      "daily_7d": [
        {
          "date": "2026-03-17",
          "close": 5001.0
        },
        {
          "date": "2026-03-18",
          "close": 4889.899902
        },
        {
          "date": "2026-03-19",
          "close": 4600.700195
        },
        {
          "date": "2026-03-20",
          "close": 4570.399902
        },
        {
          "date": "2026-03-23",
          "close": 4404.100098
        },
        {
          "date": "2026-03-24",
          "close": 4399.299805
        },
        {
          "date": "2026-03-25",
          "close": 4575.0
        }
      ],
      "vol_annual": 0.25350893,
      "vol_semiannual": 0.33693156,
      "vol_quarterly": 0.41512872,
      "vol_monthly": 0.35338149,
      "vol_weekly": 0.60357586
    },
    {
      "symbol": "SI=F",
      "name": "Silver",
      "price": 73.220001,
      "close_d1": 69.274002,
      "change_pts": 3.945999,
      "change_pct": 0.05696219,
      "daily_7d": [
        {
          "date": "2026-03-17",
          "close": 79.529999
        },
        {
          "date": "2026-03-18",
          "close": 77.237999
        },
        {
          "date": "2026-03-19",
          "close": 70.902
        },
        {
          "date": "2026-03-20",
          "close": 69.360001
        },
        {
          "date": "2026-03-23",
          "close": 69.049004
        },
        {
          "date": "2026-03-24",
          "close": 69.274002
        },
        {
          "date": "2026-03-25",
          "close": 73.190002
        }
      ],
      "vol_annual": 0.57752465,
      "vol_semiannual": 0.86721142,
      "vol_quarterly": 1.14232843,
      "vol_monthly": 0.64061422,
      "vol_weekly": 0.80494178
    },
    {
      "symbol": "HG=F",
      "name": "Copper",
      "price": 5.5385,
      "close_d1": 5.4225,
      "change_pts": 0.116,
      "change_pct": 0.02139229,
      "daily_7d": [
        {
          "date": "2026-03-17",
          "close": 5.7265
        },
        {
          "date": "2026-03-18",
          "close": 5.554
        },
        {
          "date": "2026-03-19",
          "close": 5.433
        },
        {
          "date": "2026-03-20",
          "close": 5.3425
        },
        {
          "date": "2026-03-23",
          "close": 5.4395
        },
        {
          "date": "2026-03-24",
          "close": 5.4225
        },
        {
          "date": "2026-03-25",
          "close": 5.5385
        }
      ],
      "vol_annual": 0.37346468,
      "vol_semiannual": 0.31682685,
      "vol_quarterly": 0.35909003,
      "vol_monthly": 0.24856211,
      "vol_weekly": 0.31222512
    },
    {
      "symbol": "ZS=F",
      "name": "Soybeans",
      "price": 1157.75,
      "close_d1": 1155.0,
      "change_pts": 2.75,
      "change_pct": 0.00238095,
      "daily_7d": [
        {
          "date": "2026-03-17",
          "close": 1157.0
        },
        {
          "date": "2026-03-18",
          "close": 1161.75
        },
        {
          "date": "2026-03-19",
          "close": 1168.5
        },
        {
          "date": "2026-03-20",
          "close": 1161.25
        },
        {
          "date": "2026-03-23",
          "close": 1163.5
        },
        {
          "date": "2026-03-24",
          "close": 1155.0
        },
        {
          "date": "2026-03-25",
          "close": 1157.75
        }
      ],
      "vol_annual": 0.1650962,
      "vol_semiannual": 0.16331967,
      "vol_quarterly": 0.16292678,
      "vol_monthly": 0.20165074,
      "vol_weekly": 0.09156665
    },
    {
      "symbol": "ZC=F",
      "name": "Corn",
      "price": 459.0,
      "close_d1": 462.5,
      "change_pts": -3.5,
      "change_pct": -0.00756757,
      "daily_7d": [
        {
          "date": "2026-03-17",
          "close": 454.0
        },
        {
          "date": "2026-03-18",
          "close": 463.25
        },
        {
          "date": "2026-03-19",
          "close": 469.75
        },
        {
          "date": "2026-03-20",
          "close": 465.5
        },
        {
          "date": "2026-03-23",
          "close": 459.5
        },
        {
          "date": "2026-03-24",
          "close": 462.5
        },
        {
          "date": "2026-03-25",
          "close": 459.0
        }
      ],
      "vol_annual": 0.19670509,
      "vol_semiannual": 0.16732752,
      "vol_quarterly": 0.18174276,
      "vol_monthly": 0.1873561,
      "vol_weekly": 0.18240469
    },
    {
      "symbol": "ZW=F",
      "name": "Wheat",
      "price": 581.25,
      "close_d1": 590.0,
      "change_pts": -8.75,
      "change_pct": -0.01483051,
      "daily_7d": [
        {
          "date": "2026-03-17",
          "close": 589.75
        },
        {
          "date": "2026-03-18",
          "close": 604.25
        },
        {
          "date": "2026-03-19",
          "close": 608.0
        },
        {
          "date": "2026-03-20",
          "close": 595.25
        },
        {
          "date": "2026-03-23",
          "close": 587.75
        },
        {
          "date": "2026-03-24",
          "close": 590.0
        },
        {
          "date": "2026-03-25",
          "close": 581.25
        }
      ],
      "vol_annual": 0.24346416,
      "vol_semiannual": 0.2348017,
      "vol_quarterly": 0.26857545,
      "vol_monthly": 0.37246211,
      "vol_weekly": 0.19195468
    },
    {
      "symbol": "KC=F",
      "name": "Coffee",
      "price": 313.350006,
      "close_d1": 317.850006,
      "change_pts": -4.5,
      "change_pct": -0.01415762,
      "daily_7d": [
        {
          "date": "2026-03-17",
          "close": 302.049988
        },
        {
          "date": "2026-03-18",
          "close": 299.700012
        },
        {
          "date": "2026-03-19",
          "close": 306.200012
        },
        {
          "date": "2026-03-20",
          "close": 309.75
        },
        {
          "date": "2026-03-23",
          "close": 307.0
        },
        {
          "date": "2026-03-24",
          "close": 317.850006
        },
        {
          "date": "2026-03-25",
          "close": 313.350006
        }
      ],
      "vol_annual": 0.36933254,
      "vol_semiannual": 0.34166826,
      "vol_quarterly": 0.32040782,
      "vol_monthly": 0.25401366,
      "vol_weekly": 0.32587757
    },
    {
      "symbol": "SB=F",
      "name": "Sugar",
      "price": 15.4,
      "close_d1": 15.88,
      "change_pts": -0.48,
      "change_pct": -0.03022673,
      "daily_7d": [
        {
          "date": "2026-03-17",
          "close": 14.45
        },
        {
          "date": "2026-03-18",
          "close": 14.8
        },
        {
          "date": "2026-03-19",
          "close": 15.37
        },
        {
          "date": "2026-03-20",
          "close": 15.7
        },
        {
          "date": "2026-03-23",
          "close": 15.52
        },
        {
          "date": "2026-03-24",
          "close": 15.88
        },
        {
          "date": "2026-03-25",
          "close": 15.4
        }
      ],
      "vol_annual": 0.2481968,
      "vol_semiannual": 0.24326188,
      "vol_quarterly": 0.25582811,
      "vol_monthly": 0.31497617,
      "vol_weekly": 0.44649278
    }
  ]
}