{
  "generated_at_utc": "2026-04-09T11:37:05Z",
  "source": "yfinance",
  "interval": "1d",
  "lookback": "400d",
  "trading_days": 252,
  "count": 11,
  "data": [
    {
      "symbol": "CL=F",
      "name": "Crude Oil WTI",
      "price": 99.470001,
      "close_d1": 94.410004,
      "change_pts": 5.059998,
      "change_pct": 0.05359599,
      "daily_7d": [
        {
          "date": "2026-03-31",
          "close": 101.379997
        },
        {
          "date": "2026-04-01",
          "close": 100.120003
        },
        {
          "date": "2026-04-02",
          "close": 111.540001
        },
        {
          "date": "2026-04-06",
          "close": 112.410004
        },
        {
          "date": "2026-04-07",
          "close": 112.949997
        },
        {
          "date": "2026-04-08",
          "close": 94.410004
        },
        {
          "date": "2026-04-09",
          "close": 99.470001
        }
      ],
      "vol_annual": 0.43378619,
      "vol_semiannual": 0.56623598,
      "vol_quarterly": 0.75149784,
      "vol_monthly": 1.01553587,
      "vol_weekly": 1.71370164
    },
    {
      "symbol": "BZ=F",
      "name": "Crude Oil Brent",
      "price": 98.720001,
      "close_d1": 94.75,
      "change_pts": 3.970001,
      "change_pct": 0.04189975,
      "daily_7d": [
        {
          "date": "2026-03-31",
          "close": 118.349998
        },
        {
          "date": "2026-04-01",
          "close": 101.160004
        },
        {
          "date": "2026-04-02",
          "close": 109.029999
        },
        {
          "date": "2026-04-06",
          "close": 109.769997
        },
        {
          "date": "2026-04-07",
          "close": 109.269997
        },
        {
          "date": "2026-04-08",
          "close": 94.75
        },
        {
          "date": "2026-04-09",
          "close": 98.720001
        }
      ],
      "vol_annual": 0.41734625,
      "vol_semiannual": 0.56160415,
      "vol_quarterly": 0.75117597,
      "vol_monthly": 1.06260131,
      "vol_weekly": 1.31801747
    },
    {
      "symbol": "NG=F",
      "name": "Natural Gas",
      "price": 2.728,
      "close_d1": 2.724,
      "change_pts": 0.004,
      "change_pct": 0.00146841,
      "daily_7d": [
        {
          "date": "2026-03-31",
          "close": 2.884
        },
        {
          "date": "2026-04-01",
          "close": 2.819
        },
        {
          "date": "2026-04-02",
          "close": 2.8
        },
        {
          "date": "2026-04-06",
          "close": 2.811
        },
        {
          "date": "2026-04-07",
          "close": 2.87
        },
        {
          "date": "2026-04-08",
          "close": 2.724
        },
        {
          "date": "2026-04-09",
          "close": 2.728
        }
      ],
      "vol_annual": 1.00173627,
      "vol_semiannual": 1.35833923,
      "vol_quarterly": 1.75865306,
      "vol_monthly": 0.52643296,
      "vol_weekly": 0.4351271
    },
    {
      "symbol": "GC=F",
      "name": "Gold",
      "price": 4767.700195,
      "close_d1": 4749.5,
      "change_pts": 18.200195,
      "change_pct": 0.00383202,
      "daily_7d": [
        {
          "date": "2026-03-31",
          "close": 4647.600098
        },
        {
          "date": "2026-04-01",
          "close": 4783.200195
        },
        {
          "date": "2026-04-02",
          "close": 4651.5
        },
        {
          "date": "2026-04-06",
          "close": 4656.799805
        },
        {
          "date": "2026-04-07",
          "close": 4657.100098
        },
        {
          "date": "2026-04-08",
          "close": 4749.5
        },
        {
          "date": "2026-04-09",
          "close": 4767.600098
        }
      ],
      "vol_annual": 0.25868426,
      "vol_semiannual": 0.34754378,
      "vol_quarterly": 0.42022029,
      "vol_monthly": 0.3869817,
      "vol_weekly": 0.27255492
    },
    {
      "symbol": "SI=F",
      "name": "Silver",
      "price": 74.330002,
      "close_d1": 75.223999,
      "change_pts": -0.893997,
      "change_pct": -0.01188447,
      "daily_7d": [
        {
          "date": "2026-03-31",
          "close": 74.690002
        },
        {
          "date": "2026-04-01",
          "close": 75.866997
        },
        {
          "date": "2026-04-02",
          "close": 72.735001
        },
        {
          "date": "2026-04-06",
          "close": 72.661003
        },
        {
          "date": "2026-04-07",
          "close": 71.825996
        },
        {
          "date": "2026-04-08",
          "close": 75.223999
        },
        {
          "date": "2026-04-09",
          "close": 74.330002
        }
      ],
      "vol_annual": 0.58302364,
      "vol_semiannual": 0.87648602,
      "vol_quarterly": 1.0806686,
      "vol_monthly": 0.58131945,
      "vol_weekly": 0.50871657
    },
    {
      "symbol": "HG=F",
      "name": "Copper",
      "price": 5.6955,
      "close_d1": 5.7595,
      "change_pts": -0.064,
      "change_pct": -0.0111121,
      "daily_7d": [
        {
          "date": "2026-03-31",
          "close": 5.5875
        },
        {
          "date": "2026-04-01",
          "close": 5.624
        },
        {
          "date": "2026-04-02",
          "close": 5.563
        },
        {
          "date": "2026-04-06",
          "close": 5.5835
        },
        {
          "date": "2026-04-07",
          "close": 5.5445
        },
        {
          "date": "2026-04-08",
          "close": 5.7595
        },
        {
          "date": "2026-04-09",
          "close": 5.6965
        }
      ],
      "vol_annual": 0.37499306,
      "vol_semiannual": 0.31286591,
      "vol_quarterly": 0.30894308,
      "vol_monthly": 0.26489388,
      "vol_weekly": 0.32890484
    },
    {
      "symbol": "ZS=F",
      "name": "Soybeans",
      "price": 1166.0,
      "close_d1": 1162.0,
      "change_pts": 4.0,
      "change_pct": 0.00344234,
      "daily_7d": [
        {
          "date": "2026-03-31",
          "close": 1171.0
        },
        {
          "date": "2026-04-01",
          "close": 1168.5
        },
        {
          "date": "2026-04-02",
          "close": 1163.5
        },
        {
          "date": "2026-04-06",
          "close": 1166.75
        },
        {
          "date": "2026-04-07",
          "close": 1158.25
        },
        {
          "date": "2026-04-08",
          "close": 1162.0
        },
        {
          "date": "2026-04-09",
          "close": 1166.0
        }
      ],
      "vol_annual": 0.16556478,
      "vol_semiannual": 0.16437838,
      "vol_quarterly": 0.15850792,
      "vol_monthly": 0.19929696,
      "vol_weekly": 0.07975758
    },
    {
      "symbol": "ZC=F",
      "name": "Corn",
      "price": 449.75,
      "close_d1": 447.25,
      "change_pts": 2.5,
      "change_pct": 0.00558971,
      "daily_7d": [
        {
          "date": "2026-03-31",
          "close": 457.75
        },
        {
          "date": "2026-04-01",
          "close": 454.25
        },
        {
          "date": "2026-04-02",
          "close": 452.25
        },
        {
          "date": "2026-04-06",
          "close": 454.0
        },
        {
          "date": "2026-04-07",
          "close": 449.0
        },
        {
          "date": "2026-04-08",
          "close": 447.25
        },
        {
          "date": "2026-04-09",
          "close": 449.75
        }
      ],
      "vol_annual": 0.19418233,
      "vol_semiannual": 0.1675972,
      "vol_quarterly": 0.18090114,
      "vol_monthly": 0.16064172,
      "vol_weekly": 0.10752697
    },
    {
      "symbol": "ZW=F",
      "name": "Wheat",
      "price": 588.25,
      "close_d1": 580.25,
      "change_pts": 8.0,
      "change_pct": 0.01378716,
      "daily_7d": [
        {
          "date": "2026-03-31",
          "close": 616.25
        },
        {
          "date": "2026-04-01",
          "close": 597.5
        },
        {
          "date": "2026-04-02",
          "close": 598.25
        },
        {
          "date": "2026-04-06",
          "close": 595.25
        },
        {
          "date": "2026-04-07",
          "close": 598.0
        },
        {
          "date": "2026-04-08",
          "close": 580.25
        },
        {
          "date": "2026-04-09",
          "close": 588.25
        }
      ],
      "vol_annual": 0.24279627,
      "vol_semiannual": 0.23974446,
      "vol_quarterly": 0.28118643,
      "vol_monthly": 0.30221255,
      "vol_weekly": 0.26262881
    },
    {
      "symbol": "KC=F",
      "name": "Coffee",
      "price": 274.799988,
      "close_d1": 294.049988,
      "change_pts": -19.25,
      "change_pct": -0.06546506,
      "daily_7d": [
        {
          "date": "2026-03-31",
          "close": 298.350006
        },
        {
          "date": "2026-04-01",
          "close": 297.799988
        },
        {
          "date": "2026-04-02",
          "close": 295.399994
        },
        {
          "date": "2026-04-06",
          "close": 298.049988
        },
        {
          "date": "2026-04-07",
          "close": 286.100006
        },
        {
          "date": "2026-04-08",
          "close": 294.049988
        },
        {
          "date": "2026-04-09",
          "close": 274.799988
        }
      ],
      "vol_annual": 0.37179316,
      "vol_semiannual": 0.3501863,
      "vol_quarterly": 0.35377311,
      "vol_monthly": 0.41306591,
      "vol_weekly": 0.60775111
    },
    {
      "symbol": "SB=F",
      "name": "Sugar",
      "price": 14.14,
      "close_d1": 14.23,
      "change_pts": -0.089999,
      "change_pct": -0.00632461,
      "daily_7d": [
        {
          "date": "2026-03-31",
          "close": 15.52
        },
        {
          "date": "2026-04-01",
          "close": 15.29
        },
        {
          "date": "2026-04-02",
          "close": 15.0
        },
        {
          "date": "2026-04-06",
          "close": 14.97
        },
        {
          "date": "2026-04-07",
          "close": 14.58
        },
        {
          "date": "2026-04-08",
          "close": 14.23
        },
        {
          "date": "2026-04-09",
          "close": 14.14
        }
      ],
      "vol_annual": 0.24769056,
      "vol_semiannual": 0.24658761,
      "vol_quarterly": 0.25361783,
      "vol_monthly": 0.29186091,
      "vol_weekly": 0.17306135
    }
  ]
}