{
  "generated_at_utc": "2026-04-29T17:05:23Z",
  "source": "yfinance",
  "interval": "1d",
  "lookback": "400d",
  "trading_days": 252,
  "count": 11,
  "data": [
    {
      "symbol": "CL=F",
      "name": "Crude Oil WTI",
      "price": 106.860001,
      "close_d1": 99.93,
      "change_pts": 6.93,
      "change_pct": 0.06934855,
      "daily_7d": [
        {
          "date": "2026-04-21",
          "close": 92.129997
        },
        {
          "date": "2026-04-22",
          "close": 92.959999
        },
        {
          "date": "2026-04-23",
          "close": 95.849998
        },
        {
          "date": "2026-04-24",
          "close": 94.400002
        },
        {
          "date": "2026-04-27",
          "close": 96.370003
        },
        {
          "date": "2026-04-28",
          "close": 99.93
        },
        {
          "date": "2026-04-29",
          "close": 106.860001
        }
      ],
      "vol_annual": 0.46245641,
      "vol_semiannual": 0.61442609,
      "vol_quarterly": 0.82510458,
      "vol_monthly": 1.01551959,
      "vol_weekly": 0.47118531
    },
    {
      "symbol": "BZ=F",
      "name": "Crude Oil Brent",
      "price": 110.959999,
      "close_d1": 111.260002,
      "change_pts": -0.300003,
      "change_pct": -0.00269641,
      "daily_7d": [
        {
          "date": "2026-04-21",
          "close": 98.480003
        },
        {
          "date": "2026-04-22",
          "close": 101.910004
        },
        {
          "date": "2026-04-23",
          "close": 105.07
        },
        {
          "date": "2026-04-24",
          "close": 105.330002
        },
        {
          "date": "2026-04-27",
          "close": 108.230003
        },
        {
          "date": "2026-04-28",
          "close": 111.260002
        },
        {
          "date": "2026-04-29",
          "close": 110.959999
        }
      ],
      "vol_annual": 0.43550957,
      "vol_semiannual": 0.58736119,
      "vol_quarterly": 0.79032369,
      "vol_monthly": 0.97814345,
      "vol_weekly": 0.25077701
    },
    {
      "symbol": "NG=F",
      "name": "Natural Gas",
      "price": 2.643,
      "close_d1": 2.559,
      "change_pts": 0.084,
      "change_pct": 0.03282527,
      "daily_7d": [
        {
          "date": "2026-04-21",
          "close": 2.697
        },
        {
          "date": "2026-04-22",
          "close": 2.722
        },
        {
          "date": "2026-04-23",
          "close": 2.614
        },
        {
          "date": "2026-04-24",
          "close": 2.523
        },
        {
          "date": "2026-04-27",
          "close": 2.55
        },
        {
          "date": "2026-04-28",
          "close": 2.559
        },
        {
          "date": "2026-04-29",
          "close": 2.643
        }
      ],
      "vol_annual": 0.98076508,
      "vol_semiannual": 1.34303998,
      "vol_quarterly": 1.50152119,
      "vol_monthly": 0.32770797,
      "vol_weekly": 0.49504202
    },
    {
      "symbol": "GC=F",
      "name": "Gold",
      "price": 4558.600098,
      "close_d1": 4591.5,
      "change_pts": -32.899902,
      "change_pct": -0.00716539,
      "daily_7d": [
        {
          "date": "2026-04-21",
          "close": 4698.399902
        },
        {
          "date": "2026-04-22",
          "close": 4732.5
        },
        {
          "date": "2026-04-23",
          "close": 4705.100098
        },
        {
          "date": "2026-04-24",
          "close": 4722.299805
        },
        {
          "date": "2026-04-27",
          "close": 4675.399902
        },
        {
          "date": "2026-04-28",
          "close": 4591.5
        },
        {
          "date": "2026-04-29",
          "close": 4558.899902
        }
      ],
      "vol_annual": 0.26028344,
      "vol_semiannual": 0.32606261,
      "vol_quarterly": 0.40304839,
      "vol_monthly": 0.24068469,
      "vol_weekly": 0.12448768
    },
    {
      "symbol": "SI=F",
      "name": "Silver",
      "price": 72.065002,
      "close_d1": 73.205002,
      "change_pts": -1.139999,
      "change_pct": -0.0155727,
      "daily_7d": [
        {
          "date": "2026-04-21",
          "close": 76.411003
        },
        {
          "date": "2026-04-22",
          "close": 77.892998
        },
        {
          "date": "2026-04-23",
          "close": 75.464996
        },
        {
          "date": "2026-04-24",
          "close": 76.383003
        },
        {
          "date": "2026-04-27",
          "close": 75.002998
        },
        {
          "date": "2026-04-28",
          "close": 73.205002
        },
        {
          "date": "2026-04-29",
          "close": 72.07
        }
      ],
      "vol_annual": 0.58679518,
      "vol_semiannual": 0.86426258,
      "vol_quarterly": 0.98935463,
      "vol_monthly": 0.47049368,
      "vol_weekly": 0.26407817
    },
    {
      "symbol": "HG=F",
      "name": "Copper",
      "price": 5.937,
      "close_d1": 5.9145,
      "change_pts": 0.0225,
      "change_pct": 0.00380414,
      "daily_7d": [
        {
          "date": "2026-04-21",
          "close": 6.0015
        },
        {
          "date": "2026-04-22",
          "close": 6.12
        },
        {
          "date": "2026-04-23",
          "close": 6.0755
        },
        {
          "date": "2026-04-24",
          "close": 6.0235
        },
        {
          "date": "2026-04-27",
          "close": 6.018
        },
        {
          "date": "2026-04-28",
          "close": 5.9145
        },
        {
          "date": "2026-04-29",
          "close": 5.937
        }
      ],
      "vol_annual": 0.37523787,
      "vol_semiannual": 0.2979623,
      "vol_quarterly": 0.29691429,
      "vol_monthly": 0.21877743,
      "vol_weekly": 0.12774446
    },
    {
      "symbol": "ZS=F",
      "name": "Soybeans",
      "price": 1197.75,
      "close_d1": 1173.0,
      "change_pts": 24.75,
      "change_pct": 0.02109974,
      "daily_7d": [
        {
          "date": "2026-04-21",
          "close": 1174.5
        },
        {
          "date": "2026-04-22",
          "close": 1164.5
        },
        {
          "date": "2026-04-23",
          "close": 1159.75
        },
        {
          "date": "2026-04-24",
          "close": 1163.75
        },
        {
          "date": "2026-04-27",
          "close": 1177.25
        },
        {
          "date": "2026-04-28",
          "close": 1173.0
        },
        {
          "date": "2026-04-29",
          "close": 1197.75
        }
      ],
      "vol_annual": 0.16317698,
      "vol_semiannual": 0.16313483,
      "vol_quarterly": 0.15695405,
      "vol_monthly": 0.12252583,
      "vol_weekly": 0.16877305
    },
    {
      "symbol": "ZC=F",
      "name": "Corn",
      "price": 477.25,
      "close_d1": 465.25,
      "change_pts": 12.0,
      "change_pct": 0.02579258,
      "daily_7d": [
        {
          "date": "2026-04-21",
          "close": 453.75
        },
        {
          "date": "2026-04-22",
          "close": 454.25
        },
        {
          "date": "2026-04-23",
          "close": 455.5
        },
        {
          "date": "2026-04-24",
          "close": 455.0
        },
        {
          "date": "2026-04-27",
          "close": 460.75
        },
        {
          "date": "2026-04-28",
          "close": 465.25
        },
        {
          "date": "2026-04-29",
          "close": 477.25
        }
      ],
      "vol_annual": 0.19430034,
      "vol_semiannual": 0.16937234,
      "vol_quarterly": 0.15137395,
      "vol_monthly": 0.1440036,
      "vol_weekly": 0.16295487
    },
    {
      "symbol": "ZW=F",
      "name": "Wheat",
      "price": 660.75,
      "close_d1": 649.0,
      "change_pts": 11.75,
      "change_pct": 0.01810478,
      "daily_7d": [
        {
          "date": "2026-04-21",
          "close": 605.0
        },
        {
          "date": "2026-04-22",
          "close": 599.25
        },
        {
          "date": "2026-04-23",
          "close": 610.75
        },
        {
          "date": "2026-04-24",
          "close": 608.25
        },
        {
          "date": "2026-04-27",
          "close": 621.5
        },
        {
          "date": "2026-04-28",
          "close": 649.0
        },
        {
          "date": "2026-04-29",
          "close": 660.75
        }
      ],
      "vol_annual": 0.24539792,
      "vol_semiannual": 0.2498762,
      "vol_quarterly": 0.29146314,
      "vol_monthly": 0.27975951,
      "vol_weekly": 0.26683698
    },
    {
      "symbol": "KC=F",
      "name": "Coffee",
      "price": 291.149994,
      "close_d1": 306.399994,
      "change_pts": -15.25,
      "change_pct": -0.04977154,
      "daily_7d": [
        {
          "date": "2026-04-21",
          "close": 289.0
        },
        {
          "date": "2026-04-22",
          "close": 302.399994
        },
        {
          "date": "2026-04-23",
          "close": 316.350006
        },
        {
          "date": "2026-04-24",
          "close": 309.799988
        },
        {
          "date": "2026-04-27",
          "close": 304.100006
        },
        {
          "date": "2026-04-28",
          "close": 306.399994
        },
        {
          "date": "2026-04-29",
          "close": 291.149994
        }
      ],
      "vol_annual": 0.37396697,
      "vol_semiannual": 0.34473195,
      "vol_quarterly": 0.35353587,
      "vol_monthly": 0.39717296,
      "vol_weekly": 0.57193314
    },
    {
      "symbol": "SB=F",
      "name": "Sugar",
      "price": 14.73,
      "close_d1": 14.11,
      "change_pts": 0.62,
      "change_pct": 0.04394046,
      "daily_7d": [
        {
          "date": "2026-04-21",
          "close": 13.43
        },
        {
          "date": "2026-04-22",
          "close": 13.57
        },
        {
          "date": "2026-04-23",
          "close": 13.6
        },
        {
          "date": "2026-04-24",
          "close": 13.93
        },
        {
          "date": "2026-04-27",
          "close": 13.83
        },
        {
          "date": "2026-04-28",
          "close": 14.11
        },
        {
          "date": "2026-04-29",
          "close": 14.73
        }
      ],
      "vol_annual": 0.25130305,
      "vol_semiannual": 0.24788004,
      "vol_quarterly": 0.281942,
      "vol_monthly": 0.30297075,
      "vol_weekly": 0.31116969
    }
  ]
}