{
  "generated_at_utc": "2026-03-04T16:42:35Z",
  "source": "yfinance",
  "interval": "1d",
  "lookback": "400d",
  "trading_days": 252,
  "count": 11,
  "data": [
    {
      "symbol": "CL=F",
      "name": "Crude Oil WTI",
      "price": 73.889999,
      "close_d1": 74.559998,
      "change_pts": -0.669998,
      "change_pct": -0.00898603,
      "daily_7d": [
        {
          "date": "2026-02-24",
          "close": 65.629997
        },
        {
          "date": "2026-02-25",
          "close": 65.419998
        },
        {
          "date": "2026-02-26",
          "close": 65.209999
        },
        {
          "date": "2026-02-27",
          "close": 67.019997
        },
        {
          "date": "2026-03-02",
          "close": 71.230003
        },
        {
          "date": "2026-03-03",
          "close": 74.559998
        },
        {
          "date": "2026-03-04",
          "close": 73.889999
        }
      ],
      "vol_annual": 0.31694109,
      "vol_semiannual": 0.30362263,
      "vol_quarterly": 0.33566418,
      "vol_monthly": 0.37091247,
      "vol_weekly": 0.4812357
    },
    {
      "symbol": "BZ=F",
      "name": "Crude Oil Brent",
      "price": 80.889999,
      "close_d1": 81.400002,
      "change_pts": -0.510002,
      "change_pct": -0.00626538,
      "daily_7d": [
        {
          "date": "2026-02-24",
          "close": 70.769997
        },
        {
          "date": "2026-02-25",
          "close": 70.849998
        },
        {
          "date": "2026-02-26",
          "close": 70.75
        },
        {
          "date": "2026-02-27",
          "close": 72.480003
        },
        {
          "date": "2026-03-02",
          "close": 77.739998
        },
        {
          "date": "2026-03-03",
          "close": 81.400002
        },
        {
          "date": "2026-03-04",
          "close": 80.889999
        }
      ],
      "vol_annual": 0.29661924,
      "vol_semiannual": 0.30285718,
      "vol_quarterly": 0.34323265,
      "vol_monthly": 0.37501053,
      "vol_weekly": 0.51053959
    },
    {
      "symbol": "NG=F",
      "name": "Natural Gas",
      "price": 2.915,
      "close_d1": 3.054,
      "change_pts": -0.139,
      "change_pct": -0.04551406,
      "daily_7d": [
        {
          "date": "2026-02-24",
          "close": 2.915
        },
        {
          "date": "2026-02-25",
          "close": 2.969
        },
        {
          "date": "2026-02-26",
          "close": 2.827
        },
        {
          "date": "2026-02-27",
          "close": 2.859
        },
        {
          "date": "2026-03-02",
          "close": 2.96
        },
        {
          "date": "2026-03-03",
          "close": 3.054
        },
        {
          "date": "2026-03-04",
          "close": 2.915
        }
      ],
      "vol_annual": 1.0099699,
      "vol_semiannual": 1.36375642,
      "vol_quarterly": 1.81751517,
      "vol_monthly": 0.55134707,
      "vol_weekly": 0.65518616
    },
    {
      "symbol": "GC=F",
      "name": "Gold",
      "price": 5157.5,
      "close_d1": 5107.399902,
      "change_pts": 50.100098,
      "change_pct": 0.00980932,
      "daily_7d": [
        {
          "date": "2026-02-24",
          "close": 5155.799805
        },
        {
          "date": "2026-02-25",
          "close": 5206.399902
        },
        {
          "date": "2026-02-26",
          "close": 5176.5
        },
        {
          "date": "2026-02-27",
          "close": 5230.5
        },
        {
          "date": "2026-03-02",
          "close": 5294.399902
        },
        {
          "date": "2026-03-03",
          "close": 5107.399902
        },
        {
          "date": "2026-03-04",
          "close": 5157.100098
        }
      ],
      "vol_annual": 0.24282598,
      "vol_semiannual": 0.31053501,
      "vol_quarterly": 0.37262818,
      "vol_monthly": 0.34625592,
      "vol_weekly": 0.32310124
    },
    {
      "symbol": "SI=F",
      "name": "Silver",
      "price": 83.665001,
      "close_d1": 82.922997,
      "change_pts": 0.742004,
      "change_pct": 0.00894811,
      "daily_7d": [
        {
          "date": "2026-02-24",
          "close": 87.457001
        },
        {
          "date": "2026-02-25",
          "close": 90.939003
        },
        {
          "date": "2026-02-26",
          "close": 86.998001
        },
        {
          "date": "2026-02-27",
          "close": 92.681999
        },
        {
          "date": "2026-03-02",
          "close": 88.283997
        },
        {
          "date": "2026-03-03",
          "close": 82.922997
        },
        {
          "date": "2026-03-04",
          "close": 83.665001
        }
      ],
      "vol_annual": 0.56614435,
      "vol_semiannual": 0.84430824,
      "vol_quarterly": 1.12696553,
      "vol_monthly": 0.86758982,
      "vol_weekly": 0.83040836
    },
    {
      "symbol": "HG=F",
      "name": "Copper",
      "price": 5.8895,
      "close_d1": 5.7735,
      "change_pts": 0.116,
      "change_pct": 0.02009183,
      "daily_7d": [
        {
          "date": "2026-02-24",
          "close": 5.923
        },
        {
          "date": "2026-02-25",
          "close": 5.9795
        },
        {
          "date": "2026-02-26",
          "close": 5.947
        },
        {
          "date": "2026-02-27",
          "close": 6.0045
        },
        {
          "date": "2026-03-02",
          "close": 5.8945
        },
        {
          "date": "2026-03-03",
          "close": 5.7735
        },
        {
          "date": "2026-03-04",
          "close": 5.8895
        }
      ],
      "vol_annual": 0.37146754,
      "vol_semiannual": 0.30711085,
      "vol_quarterly": 0.35885704,
      "vol_monthly": 0.33791816,
      "vol_weekly": 0.27995756
    },
    {
      "symbol": "ZS=F",
      "name": "Soybeans",
      "price": 1169.5,
      "close_d1": 1155.75,
      "change_pts": 13.75,
      "change_pct": 0.01189704,
      "daily_7d": [
        {
          "date": "2026-02-24",
          "close": 1139.5
        },
        {
          "date": "2026-02-25",
          "close": 1148.25
        },
        {
          "date": "2026-02-26",
          "close": 1147.75
        },
        {
          "date": "2026-02-27",
          "close": 1157.25
        },
        {
          "date": "2026-03-02",
          "close": 1150.0
        },
        {
          "date": "2026-03-03",
          "close": 1155.75
        },
        {
          "date": "2026-03-04",
          "close": 1169.5
        }
      ],
      "vol_annual": 0.16122708,
      "vol_semiannual": 0.15210006,
      "vol_quarterly": 0.13612298,
      "vol_monthly": 0.12311956,
      "vol_weekly": 0.11368039
    },
    {
      "symbol": "ZC=F",
      "name": "Corn",
      "price": 440.75,
      "close_d1": 434.25,
      "change_pts": 6.5,
      "change_pct": 0.01496834,
      "daily_7d": [
        {
          "date": "2026-02-24",
          "close": 427.75
        },
        {
          "date": "2026-02-25",
          "close": 430.5
        },
        {
          "date": "2026-02-26",
          "close": 433.25
        },
        {
          "date": "2026-02-27",
          "close": 438.75
        },
        {
          "date": "2026-03-02",
          "close": 433.25
        },
        {
          "date": "2026-03-03",
          "close": 434.25
        },
        {
          "date": "2026-03-04",
          "close": 440.75
        }
      ],
      "vol_annual": 0.1949541,
      "vol_semiannual": 0.17869061,
      "vol_quarterly": 0.17251265,
      "vol_monthly": 0.12243764,
      "vol_weekly": 0.17283109
    },
    {
      "symbol": "ZW=F",
      "name": "Wheat",
      "price": 566.0,
      "close_d1": 572.25,
      "change_pts": -6.25,
      "change_pct": -0.0109218,
      "daily_7d": [
        {
          "date": "2026-02-24",
          "close": 567.5
        },
        {
          "date": "2026-02-25",
          "close": 565.75
        },
        {
          "date": "2026-02-26",
          "close": 571.75
        },
        {
          "date": "2026-02-27",
          "close": 591.25
        },
        {
          "date": "2026-03-02",
          "close": 574.5
        },
        {
          "date": "2026-03-03",
          "close": 572.25
        },
        {
          "date": "2026-03-04",
          "close": 566.0
        }
      ],
      "vol_annual": 0.23374655,
      "vol_semiannual": 0.21350256,
      "vol_quarterly": 0.20984529,
      "vol_monthly": 0.25984067,
      "vol_weekly": 0.37211359
    },
    {
      "symbol": "KC=F",
      "name": "Coffee",
      "price": 286.450012,
      "close_d1": 286.950012,
      "change_pts": -0.5,
      "change_pct": -0.00174246,
      "daily_7d": [
        {
          "date": "2026-02-24",
          "close": 288.25
        },
        {
          "date": "2026-02-25",
          "close": 288.299988
        },
        {
          "date": "2026-02-26",
          "close": 286.0
        },
        {
          "date": "2026-02-27",
          "close": 284.600006
        },
        {
          "date": "2026-03-02",
          "close": 288.350006
        },
        {
          "date": "2026-03-03",
          "close": 286.950012
        },
        {
          "date": "2026-03-04",
          "close": 286.549988
        }
      ],
      "vol_annual": 0.378634,
      "vol_semiannual": 0.37454351,
      "vol_quarterly": 0.33804649,
      "vol_monthly": 0.33398901,
      "vol_weekly": 0.13229582
    },
    {
      "symbol": "SB=F",
      "name": "Sugar",
      "price": 13.73,
      "close_d1": 13.93,
      "change_pts": -0.200001,
      "change_pct": -0.01435756,
      "daily_7d": [
        {
          "date": "2026-02-24",
          "close": 14.55
        },
        {
          "date": "2026-02-25",
          "close": 14.59
        },
        {
          "date": "2026-02-26",
          "close": 14.41
        },
        {
          "date": "2026-02-27",
          "close": 14.3
        },
        {
          "date": "2026-03-02",
          "close": 13.91
        },
        {
          "date": "2026-03-03",
          "close": 13.93
        },
        {
          "date": "2026-03-04",
          "close": 13.72
        }
      ],
      "vol_annual": 0.24220226,
      "vol_semiannual": 0.22441866,
      "vol_quarterly": 0.21508267,
      "vol_monthly": 0.2307984,
      "vol_weekly": 0.16916586
    }
  ]
}